pulgon_tools_wip/Irreps_tables.py
pulgon_tools_wip/__init__.py
pulgon_tools_wip/detect_generalized_translational_group.py
pulgon_tools_wip/detect_point_group.py
pulgon_tools_wip/generate_structures.py
pulgon_tools_wip/test.py
pulgon_tools_wip/utils.py
pulgon_tools_wip-0.0.0.dist-info/LICENSE
pulgon_tools_wip-0.0.0.dist-info/METADATA
pulgon_tools_wip-0.0.0.dist-info/WHEEL
pulgon_tools_wip-0.0.0.dist-info/entry_points.txt
pulgon_tools_wip-0.0.0.dist-info/top_level.txt
pulgon_tools_wip-0.0.0.dist-info/RECORD
